studio_sdk/__init__.py
studio_sdk/_base_client.py
studio_sdk/_client.py
studio_sdk/_compat.py
studio_sdk/_constants.py
studio_sdk/_exceptions.py
studio_sdk/_files.py
studio_sdk/_models.py
studio_sdk/_qs.py
studio_sdk/_resource.py
studio_sdk/_response.py
studio_sdk/_streaming.py
studio_sdk/_types.py
studio_sdk/_version.py
studio_sdk/py.typed
studio_sdk/_utils/__init__.py
studio_sdk/_utils/_compat.py
studio_sdk/_utils/_datetime_parse.py
studio_sdk/_utils/_logs.py
studio_sdk/_utils/_proxy.py
studio_sdk/_utils/_reflection.py
studio_sdk/_utils/_resources_proxy.py
studio_sdk/_utils/_streams.py
studio_sdk/_utils/_sync.py
studio_sdk/_utils/_transform.py
studio_sdk/_utils/_typing.py
studio_sdk/_utils/_utils.py
studio_sdk/lib/.keep
studio_sdk/resources/__init__.py
studio_sdk/resources/instruments.py
studio_sdk/resources/accounts/__init__.py
studio_sdk/resources/accounts/accounts.py
studio_sdk/resources/accounts/bulk_orders.py
studio_sdk/resources/accounts/easy_borrows.py
studio_sdk/resources/accounts/holdings.py
studio_sdk/resources/accounts/inventories.py
studio_sdk/resources/accounts/locate_orders.py
studio_sdk/resources/accounts/orders.py
studio_sdk/resources/accounts/pnl_details.py
studio_sdk/resources/accounts/pnl_summary.py
studio_sdk/resources/accounts/pnl_sums.py
studio_sdk/resources/accounts/positions.py
studio_sdk/resources/accounts/trades.py
studio_sdk/resources/entities/__init__.py
studio_sdk/resources/entities/entities.py
studio_sdk/resources/entities/pnl_summaries.py
studio_sdk/resources/entities/portfolio_margins.py
studio_sdk/resources/entities/regt_margin_simulations.py
studio_sdk/resources/entities/regt_margins.py
studio_sdk/types/__init__.py
studio_sdk/types/account.py
studio_sdk/types/account_list_response.py
studio_sdk/types/entity.py
studio_sdk/types/entity_list_response.py
studio_sdk/types/instrument.py
studio_sdk/types/instrument_list_response.py
studio_sdk/types/instrument_retrieve_params.py
studio_sdk/types/pnl_summary.py
clear_street_studio_sdk-0.1.0a22.dist-info/METADATA
clear_street_studio_sdk-0.1.0a22.dist-info/WHEEL
clear_street_studio_sdk-0.1.0a22.dist-info/licenses/LICENSE
clear_street_studio_sdk-0.1.0a22.dist-info/RECORD
